relativistic_loss/__init__.py
relativistic_loss/loss.py
relativistic_loss-0.3.0.dist-info/LICENSE
relativistic_loss-0.3.0.dist-info/METADATA
relativistic_loss-0.3.0.dist-info/WHEEL
relativistic_loss-0.3.0.dist-info/top_level.txt
relativistic_loss-0.3.0.dist-info/RECORD
