Metadata-Version: 2.2
Name: relativistic_loss
Version: 0.3.0
Summary: A collection of GAN loss functions
Author: SwayStar123
License: MIT
Project-URL: Homepage, https://github.com/SwayStar123/Simple-Relativistic-GAN-Loss
Classifier: Programming Language :: Python :: 3
Classifier: License :: OSI Approved :: MIT License
Classifier: Operating System :: OS Independent
Requires-Python: >=3.6
License-File: LICENSE
Requires-Dist: torch
